{
  "$schema": "./node_modules/@angular/cli/lib/config/schema.json",
  "project": {
    "name": "sample"
  },
  "apps": [
    {
      "root": "src",
      "outDir": "dist",
      "assets": [
        "assets",
        "favicon.ico"
      ],
      "index": "index.html",
      "main": "main.ts",
      "polyfills": "polyfills.ts",
      "test": "test.ts",
      "tsconfig": "tsconfig.app.json",
      "testTsconfig": "tsconfig.spec.json",
      "prefix": "app",
      "styles": [
        "styles.css",
        "assets/css/bootstrap/bootstrap.css",
        "assets/css/bootstrap-extend/bootstrap-extend.css",
        "assets/css/site/site.css",
        "assets/js/formvalidation/formValidation.min.css",
        "assets/css/forms/validation.min.css"
      ],
      "scripts": [
        "assets/js/babel-external-helpers/babel-external-helpers.js",
        "assets/js/jquery/jquery.js",
        "assets/js/tether/tether.js",
        "assets/js/bootstrap/bootstrap.js",
        "assets/js/formvalidation/formValidation.min.js",
        "assets/js/formvalidation/framework/bootstrap4.min.js"
      ],
      "environmentSource": "environments/environment.ts",
      "environments": {
        "dev": "environments/environment.ts",
        "prod": "environments/environment.prod.ts"
      }
    }
  ],
  "e2e": {
    "protractor": {
      "config": "./protractor.conf.js"
    }
  },
  "lint": [
    {
      "project": "src/tsconfig.app.json"
    },
    {
      "project": "src/tsconfig.spec.json"
    },
    {
      "project": "e2e/tsconfig.e2e.json"
    }
  ],
  "test": {
    "karma": {
      "config": "./karma.conf.js"
    }
  },
  "defaults": {
    "styleExt": "css",
    "component": {}
  }
}
